MANIFEST.in
setup.cfg
setup.py
sphinxcontrib/__init__.py
sphinxcontrib/autojs.py
sphinxcontrib_autojs.egg-info/PKG-INFO
sphinxcontrib_autojs.egg-info/SOURCES.txt
sphinxcontrib_autojs.egg-info/dependency_links.txt
sphinxcontrib_autojs.egg-info/namespace_packages.txt
sphinxcontrib_autojs.egg-info/not-zip-safe
sphinxcontrib_autojs.egg-info/requires.txt
sphinxcontrib_autojs.egg-info/top_level.txt