Metadata-Version: 1.0
Name: sphinxcontrib-autojs
Version: 0.1dev-20110917
Summary: Sphinx "Auto JavaScript Document" extension
Home-page: https://github.com/lunant/sphinxcontrib-autojs
Author: Heungsub Lee
Author-email: h@subl.ee
License: BSD
Download-URL: http://pypi.python.org/pypi/sphinxcontrib-autojs
Platform: any
Classifier: Development Status :: 4 - Beta
Classifier: Environment :: Console
Classifier: Environment :: Web Environment
Classifier: Intended Audience :: Developers
Classifier: License :: OSI Approved :: BSD License
Classifier: Operating System :: OS Independent
Classifier: Programming Language :: Python
Classifier: Topic :: Documentation
Classifier: Topic :: Utilities
